examples/__init__.py
examples/datasets.py
examples/elementwise.py
examples/elementwise_numerical.py
examples/empirical_ntk.py
examples/function_space.py
examples/imdb.py
examples/infinite_fcn.py
examples/util.py
examples/weight_space.py
examples/experimental/__init__.py
examples/experimental/empirical_ntk_tf.py
neural_tangents/__init__.py
neural_tangents/predict.py
neural_tangents/stax.py
neural_tangents/_src/__init__.py
neural_tangents/_src/batching.py
neural_tangents/_src/empirical.py
neural_tangents/_src/monte_carlo.py
neural_tangents/_src/predict.py
neural_tangents/_src/stax/__init__.py
neural_tangents/_src/stax/branching.py
neural_tangents/_src/stax/combinators.py
neural_tangents/_src/stax/elementwise.py
neural_tangents/_src/stax/linear.py
neural_tangents/_src/stax/requirements.py
neural_tangents/_src/utils/__init__.py
neural_tangents/_src/utils/dataclasses.py
neural_tangents/_src/utils/kernel.py
neural_tangents/_src/utils/rules.py
neural_tangents/_src/utils/typing.py
neural_tangents/_src/utils/utils.py
neural_tangents/experimental/__init__.py
neural_tangents/experimental/empirical_tf/__init__.py
neural_tangents/experimental/empirical_tf/empirical.py
tests/__init__.py
tests/batching_test.py
tests/elementwise_numerical_test.py
tests/elementwise_test.py
tests/empirical_ntk_test.py
tests/empirical_test.py
tests/function_space_test.py
tests/imdb_test.py
tests/infinite_fcn_test.py
tests/monte_carlo_test.py
tests/predict_test.py
tests/rules_test.py
tests/test_utils.py
tests/weight_space_test.py
tests/experimental/__init__.py
tests/experimental/empirical_ntk_tf_test.py
tests/experimental/empirical_tf_test.py
tests/stax/__init__.py
tests/stax/branching_test.py
tests/stax/combinators_test.py
tests/stax/elementwise_test.py
tests/stax/linear_test.py
tests/stax/requirements_test.py
tests/stax/stax_test.py
neural_tangents-0.6.5.dist-info/LICENSE
neural_tangents-0.6.5.dist-info/LICENSE_SHORT
neural_tangents-0.6.5.dist-info/METADATA
neural_tangents-0.6.5.dist-info/WHEEL
neural_tangents-0.6.5.dist-info/top_level.txt
neural_tangents-0.6.5.dist-info/RECORD
