Metadata-Version: 2.1
Name: neural-tangents
Version: 0.6.5
Summary: Fast and Easy Infinite Neural Networks in Python
Home-page: https://github.com/google/neural-tangents
Author: Neural Tangents
Author-email: neural-tangents-dev@google.com
License: Apache 2.0
Download-URL: https://pypi.org/project/neural-tangents/
Project-URL: Source Code, https://github.com/google/neural-tangents
Project-URL: Paper, https://arxiv.org/abs/1912.02803
Project-URL: Finite Width NTK paper, https://arxiv.org/abs/2206.08720
Project-URL: Video, https://iclr.cc/virtual_2020/poster_SklD9yrFPS.html
Project-URL: Finite Width NTK video, https://youtu.be/8MWOhYg89fY?t=10984
Project-URL: Documentation, https://neural-tangents.readthedocs.io/en/latest/?badge=latest
Project-URL: Bug Tracker, https://github.com/google/neural-tangents/issues
Project-URL: Release Notes, https://github.com/google/neural-tangents/releases
Project-URL: PyPi, https://pypi.org/project/neural-tangents/
Project-URL: Linux Tests, https://github.com/google/neural-tangents/actions/workflows/linux.yml
Project-URL: macOS Tests, https://github.com/google/neural-tangents/actions/workflows/macos.yml
Project-URL: Pytype, https://github.com/google/neural-tangents/actions/workflows/pytype.yml
Project-URL: Coverage, https://app.codecov.io/gh/google/neural-tangents
Platform: UNKNOWN
Classifier: Programming Language :: Python :: 3.9
Classifier: Programming Language :: Python :: 3.10
Classifier: Programming Language :: Python :: 3.11
Classifier: License :: OSI Approved :: Apache Software License
Classifier: Operating System :: MacOS
Classifier: Operating System :: POSIX :: Linux
Classifier: Topic :: Software Development
Classifier: Topic :: Software Development :: Libraries
Classifier: Topic :: Software Development :: Libraries :: Python Modules
Classifier: Topic :: Scientific/Engineering
Classifier: Topic :: Scientific/Engineering :: Artificial Intelligence
Classifier: Topic :: Scientific/Engineering :: Mathematics
Classifier: Intended Audience :: Science/Research
Classifier: Intended Audience :: Developers
Classifier: Intended Audience :: Education
Classifier: Development Status :: 4 - Beta
Requires-Python: >=3.9
License-File: LICENSE
License-File: LICENSE_SHORT
Requires-Dist: jax >=0.4.16
Requires-Dist: frozendict >=2.3.8
Requires-Dist: tensorflow >=2.15.0
Requires-Dist: tf2jax >=0.3.5
Provides-Extra: testing
Requires-Dist: more-itertools ; extra == 'testing'
Requires-Dist: tensorflow-datasets ; extra == 'testing'
Requires-Dist: flax >=0.7.2 ; extra == 'testing'
